qbit/__init__.py
qbit/ca.pem
qbit/client.py
qbit/qbit_pb2.py
qbit/qbit_pb2_grpc.py
qbit-0.2.12.dist-info/METADATA
qbit-0.2.12.dist-info/WHEEL
qbit-0.2.12.dist-info/top_level.txt
qbit-0.2.12.dist-info/RECORD
