Metadata-Version: 2.1
Name: qbit
Version: 0.2.12
Summary: Client Library for 1QBit Quantum Cloud
Home-page: http://1qbit.com
Author: 1 QB Information Technologies
Author-email: info@1qbit.com
License: APLv2
Platform: UNKNOWN
Requires-Dist: requests
Requires-Dist: grpcio-tools
Requires-Dist: future
Requires-Dist: googleapis-common-protos
